LICENSE
README.md
setup.py
intertxt/__init__.py
intertxt/corpus.py
intertxt/database.py
intertxt/imports.py
intertxt/intertxt.py
intertxt/logs.py
intertxt/models.py
intertxt/rels.py
intertxt/text.py
intertxt/textlist.py
intertxt.egg-info/PKG-INFO
intertxt.egg-info/SOURCES.txt
intertxt.egg-info/dependency_links.txt
intertxt.egg-info/requires.txt
intertxt.egg-info/top_level.txt
intertxt/utils/__init__.py
intertxt/utils/downloads.py
intertxt/utils/io.py
intertxt/utils/misc.py
intertxt/utils/utils.py