Metadata-Version: 2.1
Name: intertxt
Version: 0.0.1
Summary: Resources for studying, modeling, resisting, coding, and conceptualizing the intertxtual.
Home-page: https://github.com/quadrismegistus/intertxt.git
Author: Ryan Heuser
Author-email: rj416@cam.ac.uk
License: MIT
Platform: UNKNOWN
License-File: LICENSE
